<item>
<title>[COLORred][B]12:00 - 14:00 [/COLOR][/B][COLORwhite][B]Spain - La Liga Eibar vs Real Madrid [/COLOR][/B]</title>
<info>[COLORyellow][B]Football[/COLOR][/B]</info>
<link>
<sublink>plugin://plugin.video.SportsDevil/?mode=1&amp;item=catcher%3dstreams%26url=http://wizhdsports.fi/watch/Eibar_vs_Real_Madrid_live_Football/stream10</sublink></link><referer></referer>
<thumbnail></thumbnail>
<fanart></fanart>
</item>
<item>
<title>[COLORred][B]12:30 - 14:30 [/COLOR][/B][COLORwhite][B]EPL - Manchester United vs Liverpool [/COLOR][/B]</title>
<info>[COLORyellow][B]Football[/COLOR][/B]</info>
<link>
<sublink>http://ukdvb1.uk.to:8085/TSN-1-HD/mpegts?token=hcWUvw2Ur3</sublink>
<sublink>http://ukdvb1.uk.to:8085/TSN-3-HD/mpegts?token=hcWUvw2Ur3</sublink>
<sublink>http://ukdvb1.uk.to:8085/TSN-4-HD/mpegts?token=hcWUvw2Ur3</sublink>
<sublink>http://ukdvb1.uk.to:8085/TSN-5-HD/mpegts?token=hcWUvw2Ur3</sublink>
<sublink>plugin://plugin.video.SportsDevil/?mode=1&amp;item=catcher%3dstreams%26url=http://wizhdsports.fi/watch/Manchester_United_vs_Liverpool_live_Football/stream2</sublink></link>
<referer></referer>
<thumbnail></thumbnail>
<fanart></fanart>
</item>
<item>
<title>[COLORred][B]14:15 - 16:15 [/COLOR][/B][COLORwhite][B]RBS European Rugby Ireland vs Scotland [/COLOR][/B]</title>
<info>[COLORyellow][B]Rugby[/COLOR][/B]</info>
<link>
<sublink>plugin://plugin.video.SportsDevil/?mode=1&amp;item=catcher%3dstreams%26url=http://wizhdsports.fi/watch/Ireland_vs_Scotland_live_Rugby/stream56</sublink></link>
<referer></referer>
<thumbnail></thumbnail>
<fanart></fanart>
</item>
<item>
<title>[COLORred][B]15:00 - 17:00 [/COLOR][/B][COLORwhite][B]EPL - Everton vs Brighton - Hove Albion [/COLOR][/B]</title>
<info>[COLORyellow][B]Football[/COLOR][/B]</info>
<link>
<sublink>plugin://plugin.video.SportsDevil/?mode=1&amp;item=catcher%3dstreams%26url=http://wizhdsports.fi/watch/Everton_vs_Brighton_-_Hove_Albion_live_Football/stream1</sublink></link>
<referer></referer>
<thumbnail></thumbnail>
<fanart></fanart>
</item>
<item>
<title>[COLORred][B]15:00 - 17:00 [/COLOR][/B][COLORwhite][B]EPL - Huddersfield Town vs Swansea City [/COLOR][/B]</title>
<info>[COLORyellow][B]Football[/COLOR][/B]</info>
<link>
<sublink>plugin://plugin.video.SportsDevil/?mode=1&amp;item=catcher%3dstreams%26url=http://wizhdsports.fi/watch/Huddersfield_Town_vs_Swansea_City_live_Football/stream5</sublink></link>
<referer></referer>
<thumbnail></thumbnail>
<fanart></fanart>
</item>
<item>
<title>[COLORred][B]15:00 - 17:00 [/COLOR][/B][COLORwhite][B]EPL - Newcastle United vs Southampton [/COLOR][/B]</title>
<info>[COLORyellow][B]Football[/COLOR][/B]</info>
<link>
<sublink>plugin://plugin.video.SportsDevil/?mode=1&amp;item=catcher%3dstreams%26url=http://wizhdsports.fi/watch/Newcastle_United_vs_Southampton_live_Football/stream3</sublink></link>
<referer></referer>
<thumbnail></thumbnail>
<fanart></fanart>
</item>
<item>
<title>[COLORred][B]15:00 - 17:00 [/COLOR][/B][COLORwhite][B]EPL - West Bromwich Albion vs Leicester City [/COLOR][/B]</title>
<info>[COLORyellow][B]Football[/COLOR][/B]</info>
<link>
<sublink>plugin://plugin.video.SportsDevil/?mode=1&amp;item=catcher%3dstreams%26url=http://wizhdsports.fi/watch/West_Bromwich_Albion_vs_Leicester_City_live_Football/stream2</sublink></link>
<referer></referer>
<thumbnail></thumbnail>
<fanart></fanart>
</item>
<item>
<title>[COLORred][B]15:00 - 17:00 [/COLOR][/B][COLORwhite][B]EPL - West Ham United vs Burnley [/COLOR][/B]</title>
<info>[COLORyellow][B]Football[/COLOR][/B]</info>
<link>
<sublink>plugin://plugin.video.SportsDevil/?mode=1&amp;item=catcher%3dstreams%26url=http://wizhdsports.fi/watch/West_Ham_United_vs_Burnley_live_Football/stream4</sublink></link>
<referer></referer>
<thumbnail></thumbnail>
<fanart></fanart>
</item>
<item>
<title>[COLORred][B]16:00 - 18:00 [/COLOR][/B][COLORwhite][B]Live College GameDay 2017-18 [/COLOR][/B]</title>
<info>[COLORyellow][B]Basketball[/COLOR][/B]</info>
<link>
<sublink>plugin://plugin.video.SportsDevil/?mode=1&amp;item=catcher%3dstreams%26url=http://wizhdsports.fi/watch/2017-18_live_Basketball/stream37</sublink></link>
<referer></referer>
<thumbnail></thumbnail>
<fanart></fanart>
</item>
<item>
<title>[COLORred][B]16:45 - 18:45 [/COLOR][/B][COLORwhite][B]RBS European Rugby France vs England [/COLOR][/B]</title>
<info>[COLORyellow][B]Rugby[/COLOR][/B]</info>
<link>
<sublink>plugin://plugin.video.SportsDevil/?mode=1&amp;item=catcher%3dstreams%26url=http://wizhdsports.fi/watch/France_vs_England_live_Rugby/stream56</sublink></link>
<referer></referer>
<thumbnail></thumbnail>
<fanart></fanart>
</item>
<item>
<title>[COLORred][B]16:55 - 19:00 [/COLOR][/B][COLORwhite][B]Live Betfred Super League Catalan Dragons v Hull Kingston Rovers [/COLOR][/B]</title>
<info>[COLORyellow][B]Rugby League - Domestic[/COLOR][/B]</info>
<link>
<sublink>plugin://plugin.video.SportsDevil/?mode=1&amp;item=catcher%3dstreams%26url=http://wizhdsports.fi/watch/Catalan_Dragons_v_Hull_Kingston_Rovers_live_Rugby_League_-_Domestic/stream7</sublink></link>
<referer></referer>
<thumbnail></thumbnail>
<fanart></fanart>
</item>
<item>
<title>[COLORred][B]17:30 - 19:30 [/COLOR][/B][COLORwhite][B]England - Premier League Chelsea vs Crystal Palace [/COLOR][/B]</title>
<info>[COLORyellow][B]Football[/COLOR][/B]</info>
<link>
<sublink>plugin://plugin.video.SportsDevil/?mode=1&amp;item=catcher%3dstreams%26url=http://wizhdsports.fi/watch/Chelsea_vs_Crystal_Palace_live_Football/stream1</sublink></link>
<referer></referer>
<thumbnail></thumbnail>
<fanart></fanart>
</item>
<item>
<title>[COLORred][B]17:30 - 19:30 [/COLOR][/B][COLORwhite][B]England - Championship Aston Villa vs Wolverhampton Wanderers [/COLOR][/B]</title>
<info>[COLORyellow][B]Football[/COLOR][/B]</info>
<link>
<sublink>plugin://plugin.video.SportsDevil/?mode=1&amp;item=catcher%3dstreams%26url=http://wizhdsports.fi/watch/Aston_Villa_vs_Wolverhampton_Wanderers_live_Football/stream32</sublink></link>
<referer></referer>
<thumbnail></thumbnail>
<fanart></fanart>
</item>
<item>
<title>[COLORred][B]18:00 - 21:00 [/COLOR][/B][COLORwhite][B]NHL Chicago Blackhawks @ Boston Bruins [/COLOR][/B]</title>
<info>[COLORyellow][B]Hockey[/COLOR][/B]</info>
<link>
<sublink>plugin://plugin.video.SportsDevil/?mode=1&amp;item=catcher%3dstreams%26url=http://wizhdsports.fi/watch/Chicago_Blackhawks_Boston_Bruins_live_Hockey/nhl1</sublink></link>
<referer></referer>
<thumbnail></thumbnail>
<fanart></fanart>
</item>
<item>
<title>[COLORred][B]18:00 - 21:00 [/COLOR][/B][COLORwhite][B]NHL Vegas Golden Knights @ Buffalo Sabres [/COLOR][/B]</title>
<info>[COLORyellow][B]Hockey[/COLOR][/B]</info>
<link>
<sublink>plugin://plugin.video.SportsDevil/?mode=1&amp;item=catcher%3dstreams%26url=http://wizhdsports.fi/watch/Vegas_Golden_Knights_Buffalo_Sabres_live_Hockey/nhl2</sublink></link>
<referer></referer>
<thumbnail></thumbnail>
<fanart></fanart>
</item>
<item>
<title>[COLORred][B]18:00 - 21:00 [/COLOR][/B][COLORwhite][B]NHL Montreal Canadiens @ Tampa Bay Lightning [/COLOR][/B]</title>
<info>[COLORyellow][B]Hockey[/COLOR][/B]</info>
<link>
<sublink>plugin://plugin.video.SportsDevil/?mode=1&amp;item=catcher%3dstreams%26url=http://wizhdsports.fi/watch/Montr_al_Canadiens_Tampa_Bay_Lightning_live_Hockey/nhl3</sublink></link>
<referer></referer>
<thumbnail></thumbnail>
<fanart></fanart>
</item>
<item>
<title>[COLORred][B]18:00 - 21:00 [/COLOR][/B][COLORwhite][B]NHL Winnipeg Jets @ Philadelphia Flyers [/COLOR][/B]</title>
<info>[COLORyellow][B]Hockey[/COLOR][/B]</info>
<link>
<sublink>plugin://plugin.video.SportsDevil/?mode=1&amp;item=catcher%3dstreams%26url=http://wizhdsports.fi/watch/Winnipeg_Jets_Philadelphia_Flyers_live_Hockey/nhl4</sublink></link>
<referer></referer>
<thumbnail></thumbnail>
<fanart></fanart>
</item>
<item>
<title>[COLORred][B]20:00 - 23:00 [/COLOR][/B][COLORwhite][B]NHL Arizona Coyotes @ Colorado Avalanche [/COLOR][/B]</title>
<info>[COLORyellow][B]Hockey[/COLOR][/B]</info>
<link>
<sublink>plugin://plugin.video.SportsDevil/?mode=1&amp;item=catcher%3dstreams%26url=http://wizhdsports.fi/watch/Arizona_Coyotes_Colorado_Avalanche_live_Hockey/nhl5</sublink></link>
<referer></referer>
<thumbnail></thumbnail>
<fanart></fanart>
</item>
<item>
<title>[COLORred][B]20:30 - 00:00 [/COLOR][/B][COLORwhite][B]Live NASCAR Xfinity Series 2018 DC Solar 200 [/COLOR][/B]</title>
<info>[COLORyellow][B]Motor Sport[/COLOR][/B]</info>
<link>
<sublink>plugin://plugin.video.SportsDevil/?mode=1&amp;item=catcher%3dstreams%26url=http://wizhdsports.fi/watch/2018_DC_Solar_200_live_Motor_Sport/stream36</sublink></link><referer></referer>
<thumbnail></thumbnail>
<fanart></fanart>
</item>
<item>
<title>[COLORred][B]21:00 - 00:00 [/COLOR][/B][COLORwhite][B]NHL St. Louis Blues @ Los Angeles Kings [/COLOR][/B]</title>
<info>[COLORyellow][B]Hockey[/COLOR][/B]</info>
<link>
<sublink>plugin://plugin.video.SportsDevil/?mode=1&amp;item=catcher%3dstreams%26url=http://wizhdsports.fi/watch/St_Louis_Blues_Los_Angeles_Kings_live_Hockey/nhl6</sublink></link>
<referer></referer>
<thumbnail></thumbnail>
<fanart></fanart>
</item>
<item>
<title>[COLORred][B]21:00 - 00:00 [/COLOR][/B][COLORwhite][B]NHL Washington Capitals @ San Jose Sharks [/COLOR][/B]</title>
<info>[COLORyellow][B]Hockey[/COLOR][/B]</info>
<link>
<sublink>plugin://plugin.video.SportsDevil/?mode=1&amp;item=catcher%3dstreams%26url=http://wizhdsports.fi/watch/Washington_Capitals_San_Jose_Sharks_live_Hockey/nhl7</sublink></link>
<referer></referer>
<thumbnail></thumbnail>
<fanart></fanart>
</item>
<item>
<title>[COLORred][B]21:15 - 00:00 [/COLOR][/B][COLORwhite][B]Boxing Brian Carlos Castano vs Cedric Vitu [/COLOR][/B]</title>
<info>[COLORyellow][B]Boxing[/COLOR][/B]</info>
<link>
<sublink>plugin://plugin.video.SportsDevil/?mode=1&amp;item=catcher%3dstreams%26url=http://wizhdsports.fi/watch/Brian_Carlos_Castano_vs_Cedric_Vitu_live_Boxing/stream8</sublink></link>
<referer></referer>
<thumbnail></thumbnail>
<fanart></fanart>
</item>
<item>
<title>[COLORred][B]22:00 - 01:00 [/COLOR][/B][COLORwhite][B]Live NCAA Indoor Track - Field 2018 [/COLOR][/B]</title>
<info>[COLORyellow][B]Athletics[/COLOR][/B]</info>
<link>
<sublink>plugin://plugin.video.SportsDevil/?mode=1&amp;item=catcher%3dstreams%26url=http://wizhdsports.fi/watch/2018_live_Athletics/btsports2</sublink></link>
<referer></referer>
<thumbnail></thumbnail>
<fanart></fanart>
</item>
<item>
<title>[COLORred][B]22:00 - 01:00 [/COLOR][/B][COLORwhite][B]NBA Phoenix Suns @ Charlotte Hornets [/COLOR][/B]</title>
<info>[COLORyellow][B]NBA[/COLOR][/B]</info>
<link>
<sublink>plugin://plugin.video.SportsDevil/?mode=1&amp;item=catcher%3dstreams%26url=http://wizhdsports.fi/watch/Phoenix_Suns_Charlotte_Hornets_live_NBA/nba1</sublink></link>
<referer></referer>
<thumbnail></thumbnail>
<fanart></fanart>
</item>
<item>
<title>[COLORred][B]00:00 - 03:00 [/COLOR][/B][COLORwhite][B]NHL Pittsburgh Penguins @ Toronto Maple Leafs [/COLOR][/B]</title>
<info>[COLORyellow][B]Hockey[/COLOR][/B]</info>
<link>
<sublink>plugin://plugin.video.SportsDevil/?mode=1&amp;item=catcher%3dstreams%26url=http://wizhdsports.fi/watch/Pittsburgh_Penguins_Toronto_Maple_Leafs_live_Hockey/nhl8</sublink></link>
<referer></referer>
<thumbnail></thumbnail>
<fanart></fanart>
</item>
<item>
<title>[COLORred][B]00:00 - 03:00 [/COLOR][/B][COLORwhite][B]NHL New York Rangers @ Florida Panthers [/COLOR][/B]</title>
<info>[COLORyellow][B]Hockey[/COLOR][/B]</info>
<link>
<sublink>plugin://plugin.video.SportsDevil/?mode=1&amp;item=catcher%3dstreams%26url=http://wizhdsports.fi/watch/New_York_Rangers_Florida_Panthers_live_Hockey/nhl9</sublink></link>
<referer></referer>
<thumbnail></thumbnail>
<fanart></fanart>
</item>
<item>
<title>[COLORred][B]00:30 - 03:30 [/COLOR][/B][COLORwhite][B]NBA Washington Wizards @ Miami Heat [/COLOR][/B]</title>
<info>[COLORyellow][B]NBA[/COLOR][/B]</info>
<link>
<sublink>plugin://plugin.video.SportsDevil/?mode=1&amp;item=catcher%3dstreams%26url=http://wizhdsports.fi/watch/Washington_Wizards_Miami_Heat_live_NBA/nba2</sublink></link><referer></referer>
<thumbnail></thumbnail>
<fanart></fanart>
</item>
<item>
<title>[COLORred][B]01:00 - 04:00 [/COLOR][/B][COLORwhite][B]NHL New Jersey Devils @ Nashville Predators [/COLOR][/B]</title>
<info>[COLORyellow][B]Hockey[/COLOR][/B]</info>
<link>
<sublink>plugin://plugin.video.SportsDevil/?mode=1&amp;item=catcher%3dstreams%26url=http://wizhdsports.fi/watch/New_Jersey_Devils_Nashville_Predators_live_Hockey/nhl10</sublink></link>
<referer></referer>
<thumbnail></thumbnail>
<fanart></fanart>
</item>
<item>
<title>[COLORred][B]01:30 - 04:30 [/COLOR][/B][COLORwhite][B]NBA Memphis Grizzlies @ Dallas Maverick [/COLOR][/B]</title>
<info>[COLORyellow][B]NBA[/COLOR][/B]</info>
<link>
<sublink>plugin://plugin.video.SportsDevil/?mode=1&amp;item=catcher%3dstreams%26url=http://wizhdsports.fi/watch/Memphis_Grizzlies_Dallas_Maverick_live_NBA/nba3</sublink></link>
<referer></referer>
<thumbnail></thumbnail>
<fanart></fanart>
</item>
<item>
<title>[COLORred][B]01:30 - 04:30 [/COLOR][/B][COLORwhite][B]NBA San Antonio Spurs @ Oklahoma City Thunder [/COLOR][/B]</title>
<info>[COLORyellow][B]NBA[/COLOR][/B]</info>
<link>
<sublink>plugin://plugin.video.SportsDevil/?mode=1&amp;item=catcher%3dstreams%26url=http://wizhdsports.fi/watch/San_Antonio_Spurs_Oklahoma_City_Thunder_live_NBA/nba4</sublink></link>
<referer></referer>
<thumbnail></thumbnail>
<fanart></fanart>
</item>
<item>
<title>[COLORred][B]03:00 - 06:00 [/COLOR][/B][COLORwhite][B]NHL Minnesota Wild @ Edmonton Oilers [/COLOR][/B]</title>
<info>[COLORyellow][B]Hockey[/COLOR][/B]</info>
<link>
<sublink>plugin://plugin.video.SportsDevil/?mode=1&amp;item=catcher%3dstreams%26url=http://wizhdsports.fi/watch/Minnesota_Wild_Edmonton_Oilers_live_Hockey/nhl11</sublink></link>
<referer></referer>
<thumbnail></thumbnail>
<fanart></fanart>
</item>
<item>
<title>[COLORred][B]03:00 - 06:00 [/COLOR][/B][COLORwhite][B]Boxing Oscar Valdez vs Scott Quigg [/COLOR][/B]</title>
<info>[COLORyellow][B]Boxing[/COLOR][/B]</info>
<link>
<sublink>plugin://plugin.video.SportsDevil/?mode=1&amp;item=catcher%3dstreams%26url=http://wizhdsports.fi/watch/Oscar_Valdez_vs_Scott_Quigg_live_Boxing/skysportsmainevent</sublink></link>
<referer></referer>
<thumbnail></thumbnail>
<fanart></fanart>
</item>
<item>
<title>[COLORred][B]03:00 - 06:00 [/COLOR][/B][COLORwhite][B]Boxing Mikey Gracia vs Sergey Lipnites [/COLOR][/B]</title>
<info>[COLORyellow][B]Boxing[/COLOR][/B]</info>
<link>
<sublink>plugin://plugin.video.SportsDevil/?mode=1&amp;item=catcher%3dstreams%26url=http://wizhdsports.fi/watch/Mikey_Gracia_vs_Sergey_Lipnites_live_Boxing/stream2</sublink></link>
<referer></referer>
<thumbnail></thumbnail>
<fanart></fanart>
</item>
<item>
<title>[COLORred][B]03:30 - 06:30 [/COLOR][/B][COLORwhite][B]NBA Orlando Magic @ LA Clippers [/COLOR][/B]</title>
<info>[COLORyellow][B]NBA[/COLOR][/B]</info>
<link>
<sublink>plugin://plugin.video.SportsDevil/?mode=1&amp;item=catcher%3dstreams%26url=http://wizhdsports.fi/watch/Orlando_Magic_LA_Clippers_live_NBA/nba5</sublink></link>
<referer></referer>
<thumbnail></thumbnail>
<fanart></fanart>
</item>
