
<item>
<title>[COLORred][B]12:00 - 14:00 [/COLOR][/B][COLORwhite][B]Spain - La Liga Real Madrid vs Barcelona [/COLOR][/B]</title>
<info>[COLORyellow][B]Football[/COLOR][/B]</info>
<link>
<sublink>plugin://plugin.video.SportsDevil/?mode=1&amp;item=catcher%3dstreams%26url=http://wizhdsports.fi/watch/Real_Madrid_vs_Barcelona_live_Football/stream10</sublink></link>
<referer></referer>
<thumbnail></thumbnail>
<fanart></fanart>
</plugin>
<item>
<title>[COLORred][B]12:30 - 14:30 [/COLOR][/B][COLORwhite][B]Scotland - Scottish Premiership Kilmarnock vs Rangers [/COLOR][/B]</title>
<info>[COLORyellow][B]Football[/COLOR][/B]</info>
<link>
<sublink>plugin://plugin.video.SportsDevil/?mode=1&amp;item=catcher%3dstreams%26url=http://wizhdsports.fi/watch/Kilmarnock_vs_Rangers_live_Football/btsports1</sublink></link>
<referer></referer>
<thumbnail></thumbnail>
<fanart></fanart>
</plugin>
<item>
<title>[COLORred][B]12:30 - 14:30 [/COLOR][/B][COLORwhite][B]England - Premier League Everton vs Chelsea [/COLOR][/B]</title>
<info>[COLORyellow][B]Football[/COLOR][/B]</info>
<link>
<sublink>plugin://plugin.video.SportsDevil/?mode=1&amp;item=catcher%3dstreams%26url=http://wizhdsports.fi/watch/Everton_vs_Chelsea_live_Football/stream1</sublink></link>
<referer></referer>
<thumbnail></thumbnail>
<fanart></fanart>
</plugin>
<item>
<title>[COLORred][B]13:00 - 17:00 [/COLOR][/B][COLORwhite][B]Live World Darts Championship 2018 Day 10: Afternoon Session [/COLOR][/B]</title>
<info>[COLORyellow][B]Darts[/COLOR][/B]</info>
<link>
<sublink>plugin://plugin.video.SportsDevil/?mode=1&amp;item=catcher%3dstreams%26url=http://wizhdsports.fi/watch/2018_Day_10_Afternoon_Session_live_Darts/stream28</sublink></link>
<referer></referer>
<thumbnail></thumbnail>
<fanart></fanart>
</plugin>
<item>
<title>[COLORred][B]15:00 - 17:00 [/COLOR][/B][COLORwhite][B]Scotland - Scottish Premiership Celtic vs Aberdeen [/COLOR][/B]</title>
<info>[COLORyellow][B]Football[/COLOR][/B]</info>
<link>
<sublink>plugin://plugin.video.SportsDevil/?mode=1&amp;item=catcher%3dstreams%26url=http://wizhdsports.fi/watch/Celtic_vs_Aberdeen_live_Football/stream42</sublink></link>
<referer></referer>
<thumbnail></thumbnail>
<fanart></fanart>
</plugin>
<item>
<title>[COLORred][B]15:00 - 17:00 [/COLOR][/B][COLORwhite][B]England - Premier League Brighton & Hove Albion vs Watford [/COLOR][/B]</title>
<info>[COLORyellow][B]Football[/COLOR][/B]</info>
<link>
<sublink>plugin://plugin.video.SportsDevil/?mode=1&amp;item=catcher%3dstreams%26url=http://wizhdsports.fi/watch/Brighton_Hove_Albion_vs_Watford_live_Football/stream3</sublink></link>
<referer></referer>
<thumbnail></thumbnail>
<fanart></fanart>
</plugin>
<item>
<title>[COLORred][B]15:00 - 17:00 [/COLOR][/B][COLORwhite][B]England - Premier League Manchester City vs AFC Bournemouth [/COLOR][/B]</title>
<info>[COLORyellow][B]Football[/COLOR][/B]</info>
<link>
<sublink>plugin://plugin.video.SportsDevil/?mode=1&amp;item=catcher%3dstreams%26url=http://wizhdsports.fi/watch/Manchester_City_vs_AFC_Bournemouth_live_Football/stream2</sublink></link>
<referer></referer>
<thumbnail></thumbnail>
<fanart></fanart>
</plugin>
<item>
<title>[COLORred][B]15:00 - 17:00 [/COLOR][/B][COLORwhite][B]England - Premier League Southampton vs Huddersfield Town [/COLOR][/B]</title>
<info>[COLORyellow][B]Football[/COLOR][/B]</info>
<link>
<sublink>plugin://plugin.video.SportsDevil/?mode=1&amp;item=catcher%3dstreams%26url=http://wizhdsports.fi/watch/Southampton_vs_Huddersfield_Town_live_Football/stream5</sublink></link>
<referer></referer>
<thumbnail></thumbnail>
<fanart></fanart>
</plugin>
<item>
<title>[COLORred][B]15:00 - 17:00 [/COLOR][/B][COLORwhite][B]England - Premier League Stoke City vs West Bromwich Albion [/COLOR][/B]</title>
<info>[COLORyellow][B]Football[/COLOR][/B]</info>
<link>
<sublink>plugin://plugin.video.SportsDevil/?mode=1&amp;item=catcher%3dstreams%26url=http://wizhdsports.fi/watch/Stoke_City_vs_West_Bromwich_Albion_live_Football/stream6</sublink></link>
<referer></referer>
<thumbnail></thumbnail>
<fanart></fanart>
</plugin>
<item>
<title>[COLORred][B]15:00 - 17:00 [/COLOR][/B][COLORwhite][B]England - Premier League Swansea City vs Crystal Palace [/COLOR][/B]</title>
<info>[COLORyellow][B]Football[/COLOR][/B]</info>
<link>
<sublink>plugin://plugin.video.SportsDevil/?mode=1&amp;item=catcher%3dstreams%26url=http://wizhdsports.fi/watch/Swansea_City_vs_Crystal_Palace_live_Football/stream1</sublink></link>
<referer></referer>
<thumbnail></thumbnail>
<fanart></fanart>
</plugin>
<item>
<title>[COLORred][B]15:00 - 17:00 [/COLOR][/B][COLORwhite][B]England - Premier League West Ham United vs Newcastle United [/COLOR][/B]</title>
<info>[COLORyellow][B]Football[/COLOR][/B]</info>
<link>
<sublink>plugin://plugin.video.SportsDevil/?mode=1&amp;item=catcher%3dstreams%26url=http://wizhdsports.fi/watch/West_Ham_United_vs_Newcastle_United_live_Football/stream7</sublink></link>
<referer></referer>
<thumbnail></thumbnail>
<fanart></fanart>
</plugin>
<item>
<title>[COLORred][B]15:00 - 17:00 [/COLOR][/B][COLORwhite][B]England - Championship Sheffield Wednesday vs Middlesbrough [/COLOR][/B]</title>
<info>[COLORyellow][B]Football[/COLOR][/B]</info>
<link>
<sublink>plugin://plugin.video.SportsDevil/?mode=1&amp;item=catcher%3dstreams%26url=http://wizhdsports.fi/watch/Sheffield_Wednesday_vs_Middlesbrough_live_Football/stream45</sublink></link>
<referer></referer>
<thumbnail></thumbnail>
<fanart></fanart>
</plugin>
<item>
<title>[COLORred][B]17:00 - 20:30 [/COLOR][/B][COLORwhite][B]Live CFB: Birmingham Bowl South Florida vs. Texas Tech [/COLOR][/B]</title>
<info>[COLORyellow][B]American Football[/COLOR][/B]</info>
<link>
<sublink>plugin://plugin.video.SportsDevil/?mode=1&amp;item=catcher%3dstreams%26url=http://wizhdsports.fi/watch/South_Florida_vs_Texas_Tech_live_American_Football/stream37</sublink></link>
<referer></referer>
<thumbnail></thumbnail>
<fanart></fanart>
</plugin>
<item>
<title>[COLORred][B]17:30 - 19:30 [/COLOR][/B][COLORwhite][B]England - Premier League Burnley vs Tottenham Hotspur [/COLOR][/B]</title>
<info>[COLORyellow][B]Football[/COLOR][/B]</info>
<link>
<sublink>plugin://plugin.video.SportsDevil/?mode=1&amp;item=catcher%3dstreams%26url=http://wizhdsports.fi/watch/Burnley_vs_Tottenham_Hotspur_live_Football/btsports1</sublink></link>
<referer></referer>
<thumbnail></thumbnail>
<fanart></fanart>
</plugin>
<item>
<title>[COLORred][B]17:30 - 19:30 [/COLOR][/B][COLORwhite][B]England - Championship Aston Villa vs Sheffield United [/COLOR][/B]</title>
<info>[COLORyellow][B]Football[/COLOR][/B]</info>
<link>
<sublink>plugin://plugin.video.SportsDevil/?mode=1&amp;item=catcher%3dstreams%26url=http://wizhdsports.fi/watch/Aston_Villa_vs_Sheffield_United_live_Football/stream32</sublink></link>
<referer></referer>
<thumbnail></thumbnail>
<fanart></fanart>
</plugin>
<item>
<title>[COLORred][B]18:00 - 21:00 [/COLOR][/B][COLORwhite][B]NHL Detroit Red Wings at Boston Bruins [/COLOR][/B]</title>
<info>[COLORyellow][B]Hockey[/COLOR][/B]</info>
<link>
<sublink>plugin://plugin.video.SportsDevil/?mode=1&amp;item=catcher%3dstreams%26url=http://wizhdsports.fi/watch/Detroit_Red_Wings_at_Boston_Bruins_live_Hockey/nhl1</sublink></link>
<referer></referer>
<thumbnail></thumbnail>
<fanart></fanart>
</plugin>
<item>
<title>[COLORred][B]18:00 - 21:00 [/COLOR][/B][COLORwhite][B]NHL Winnipeg Jets at New York Islanders [/COLOR][/B]</title>
<info>[COLORyellow][B]Hockey[/COLOR][/B]</info>
<link>
<sublink>plugin://plugin.video.SportsDevil/?mode=1&amp;item=catcher%3dstreams%26url=http://wizhdsports.fi/watch/Winnipeg_Jets_at_New_York_Islanders_live_Hockey/nhl2</sublink></link>
<referer></referer>
<thumbnail></thumbnail>
<fanart></fanart>
</plugin>
<item>
<title>[COLORred][B]19:00 - 23:00 [/COLOR][/B][COLORwhite][B]Live World Darts Championship 2018 Day 10: Evening Session [/COLOR][/B]</title>
<info>[COLORyellow][B]Darts[/COLOR][/B]</info>
<link>
<sublink>plugin://plugin.video.SportsDevil/?mode=1&amp;item=catcher%3dstreams%26url=http://wizhdsports.fi/watch/2018_Day_10_Evening_Session_live_Darts/stream28</sublink></link>
<referer></referer>
<thumbnail></thumbnail>
<fanart></fanart>
</plugin>
<item>
<title>[COLORred][B]19:45 - 21:45 [/COLOR][/B][COLORwhite][B]England - Premier League Leicester City vs Manchester United [/COLOR][/B]</title>
<info>[COLORyellow][B]Football[/COLOR][/B]</info>
<link>
<sublink>plugin://plugin.video.SportsDevil/?mode=1&amp;item=catcher%3dstreams%26url=http://wizhdsports.fi/watch/Leicester_City_vs_Manchester_United_live_Football/skysportsmainevent</sublink></link>
<referer></referer>
<thumbnail></thumbnail>
<fanart></fanart>
</plugin>
<item>
<title>[COLORred][B]20:30 - 00:00 [/COLOR][/B][COLORwhite][B]Live CFB: Armed Forces Bowl Army vs. San Diego State [/COLOR][/B]</title>
<info>[COLORyellow][B]American Football[/COLOR][/B]</info>
<link>
<sublink>plugin://plugin.video.SportsDevil/?mode=1&amp;item=catcher%3dstreams%26url=http://wizhdsports.fi/watch/Army_vs_San_Diego_State_live_American_Football/stream37</sublink></link>
<referer></referer>
<thumbnail></thumbnail>
<fanart></fanart>
</plugin>
<item>
<title>[COLORred][B]21:30 - 01:00 [/COLOR][/B][COLORwhite][B]NFL Indianapolis Colts at Baltimore Ravens [/COLOR][/B]</title>
<info>[COLORyellow][B]NFL[/COLOR][/B]</info>
<link>
<sublink>plugin://plugin.video.SportsDevil/?mode=1&amp;item=catcher%3dstreams%26url=http://wizhdsports.fi/watch/Indianapolis_Colts_at_Baltimore_Ravens_live_NFL/skysportsaction</sublink></link>
<referer></referer>
<thumbnail></thumbnail>
<fanart></fanart>
</plugin>
<item>
<title>[COLORred][B]22:00 - 01:00 [/COLOR][/B][COLORwhite][B]NBA Philadelphia 76ers at Toronto Raptors [/COLOR][/B]</title><info>[COLORyellow][B]NBA[/COLOR][/B]</info>
<link>
<sublink>plugin://plugin.video.SportsDevil/?mode=1&amp;item=catcher%3dstreams%26url=http://wizhdsports.fi/watch/Philadelphia_76ers_at_Toronto_Raptors_live_NBA/nba1</sublink></link>
<referer></referer>
<thumbnail></thumbnail>
<fanart></fanart>
</plugin>
<item>
<title>[COLORred][B]00:00 - 03:00 [/COLOR][/B][COLORwhite][B]NBA Milwaukee Bucks at Charlotte Hornets [/COLOR][/B]</title>
<info>[COLORyellow][B]NBA[/COLOR][/B]</info>
<link>
<sublink>plugin://plugin.video.SportsDevil/?mode=1&amp;item=catcher%3dstreams%26url=http://wizhdsports.fi/watch/Milwaukee_Bucks_at_Charlotte_Hornets_live_NBA/nba2</sublink></link>
<referer></referer>
<thumbnail></thumbnail>
<fanart></fanart>
</plugin>
<item>
<title>[COLORred][B]00:00 - 03:00 [/COLOR][/B][COLORwhite][B]NBA Brooklyn Nets at Indiana Pacers [/COLOR][/B]</title>
<info>[COLORyellow][B]NBA[/COLOR][/B]</info>
<link>
<sublink>plugin://plugin.video.SportsDevil/?mode=1&amp;item=catcher%3dstreams%26url=http://wizhdsports.fi/watch/Brooklyn_Nets_at_Indiana_Pacers_live_NBA/nba3</sublink></link>
<referer></referer>
<thumbnail></thumbnail>
<fanart></fanart>
</plugin>
<item>
<title>[COLORred][B]00:00 - 03:00 [/COLOR][/B][COLORwhite][B]NBA Orlando Magic at Washington Wizards [/COLOR][/B]</title>
<info>[COLORyellow][B]NBA[/COLOR][/B]</info>
<link>
<sublink>plugin://plugin.video.SportsDevil/?mode=1&amp;item=catcher%3dstreams%26url=http://wizhdsports.fi/watch/Orlando_Magic_at_Washington_Wizards_live_NBA/nba4</sublink></link>
<referer></referer>
<thumbnail></thumbnail>
<fanart></fanart>
</plugin>
<item>
<title>[COLORred][B]00:00 - 03:00 [/COLOR][/B][COLORwhite][B]NHL Montreal Canadiens at Edmonton Oilers [/COLOR][/B]</title><info>[COLORyellow][B]Hockey[/COLOR][/B]</info>
<link>
<sublink>plugin://plugin.video.SportsDevil/?mode=1&amp;item=catcher%3dstreams%26url=http://wizhdsports.fi/watch/Montreal_Canadiens_at_Edmonton_Oilers_live_Hockey/nhl3</sublink></link>
<referer></referer>
<thumbnail></thumbnail>
<fanart></fanart>
</plugin>
<item>
<title>[COLORred][B]00:00 - 03:00 [/COLOR][/B][COLORwhite][B]NHL Minnesota Wild at Tampa Bay Lightning [/COLOR][/B]</title><info>[COLORyellow][B]Hockey[/COLOR][/B]</info>
<link>
<sublink>plugin://plugin.video.SportsDevil/?mode=1&amp;item=catcher%3dstreams%26url=http://wizhdsports.fi/watch/Minnesota_Wild_at_Tampa_Bay_Lightning_live_Hockey/nhl4</sublink></link>
<referer></referer>
<thumbnail></thumbnail>
<fanart></fanart>
</plugin>
<item>
<title>[COLORred][B]00:00 - 03:00 [/COLOR][/B][COLORwhite][B]NHL Ottawa Senators at Florida Panthers [/COLOR][/B]</title>
<info>[COLORyellow][B]Hockey[/COLOR][/B]</info>
<link>
<sublink>plugin://plugin.video.SportsDevil/?mode=1&amp;item=catcher%3dstreams%26url=http://wizhdsports.fi/watch/Ottawa_Senators_at_Florida_Panthers_live_Hockey/nhl5</sublink></link>
<referer></referer>
<thumbnail></thumbnail>
<fanart></fanart>
</plugin>
<item>
<title>[COLORred][B]00:00 - 03:00 [/COLOR][/B][COLORwhite][B]NHL Chicago Blackhawks at New Jersey Devils [/COLOR][/B]</title>
<info>[COLORyellow][B]Hockey[/COLOR][/B]</info>
<link>
<sublink>plugin://plugin.video.SportsDevil/?mode=1&amp;item=catcher%3dstreams%26url=http://wizhdsports.fi/watch/Chicago_Blackhawks_at_New_Jersey_Devils_live_Hockey/nhl6</sublink></link>
<referer></referer>
<thumbnail></thumbnail>
<fanart></fanart>
</plugin>
<item>
<title>[COLORred][B]00:00 - 03:00 [/COLOR][/B][COLORwhite][B]NHL Toronto Maple Leafs at New York Rangers [/COLOR][/B]</title>
<info>[COLORyellow][B]Hockey[/COLOR][/B]</info>
<link>
<sublink>plugin://plugin.video.SportsDevil/?mode=1&amp;item=catcher%3dstreams%26url=http://wizhdsports.fi/watch/Toronto_Maple_Leafs_at_New_York_Rangers_live_Hockey/nhl7</sublink></link>
<referer></referer>
<thumbnail></thumbnail>
<fanart></fanart>
</plugin>
<item>
<title>[COLORred][B]00:00 - 03:00 [/COLOR][/B][COLORwhite][B]NHL Anaheim Ducks at Pittsburgh Penguins [/COLOR][/B]</title>
<info>[COLORyellow][B]Hockey[/COLOR][/B]</info>
<link>
<sublink>plugin://plugin.video.SportsDevil/?mode=1&amp;item=catcher%3dstreams%26url=http://wizhdsports.fi/watch/Anaheim_Ducks_at_Pittsburgh_Penguins_live_Hockey/nhl8</sublink></link>
<referer></referer>
<thumbnail></thumbnail>
<fanart></fanart>
</plugin>
<item>
<title>[COLORred][B]00:00 - 03:00 [/COLOR][/B][COLORwhite][B]NHL Buffalo Sabres at Carolina Hurricanes [/COLOR][/B]</title><info>[COLORyellow][B]Hockey[/COLOR][/B]</info>
<link>
<sublink>plugin://plugin.video.SportsDevil/?mode=1&amp;item=catcher%3dstreams%26url=http://wizhdsports.fi/watch/Buffalo_Sabres_at_Carolina_Hurricanes_live_Hockey/nhl9</sublink></link>
<referer></referer>
<thumbnail></thumbnail>
<fanart></fanart>
</plugin>
<item>
<title>[COLORred][B]00:00 - 03:00 [/COLOR][/B][COLORwhite][B]NHL Philadelphia Flyers at Columbus Blue Jackets [/COLOR][/B]</title>
<info>[COLORyellow][B]Hockey[/COLOR][/B]</info>
<link>
<sublink>plugin://plugin.video.SportsDevil/?mode=1&amp;item=catcher%3dstreams%26url=http://wizhdsports.fi/watch/Philadelphia_Flyers_at_Columbus_Blue_Jackets_live_Hockey/nhl10</sublink></link>
<referer></referer>
<thumbnail></thumbnail>
<fanart></fanart>
</plugin>
<item>
<title>[COLORred][B]00:00 - 03:00 [/COLOR][/B][COLORwhite][B]Live CFB: Dollar General Bowl Appalachian State vs. Toledo [/COLOR][/B]</title>
<info>[COLORyellow][B]NFL[/COLOR][/B]</info>
<link>
<sublink>plugin://plugin.video.SportsDevil/?mode=1&amp;item=catcher%3dstreams%26url=http://wizhdsports.fi/watch/Appalachian_State_vs_Toledo_live_NFL/stream37</sublink></link>
<referer></referer>
<thumbnail></thumbnail>
<fanart></fanart>
</plugin>
<item>
<title>[COLORred][B]00:30 - 03:30 [/COLOR][/B][COLORwhite][B]NBA Dallas Mavericks at Atlanta Hawks [/COLOR][/B]</title>
<info>[COLORyellow][B]NBA[/COLOR][/B]</info>
<link>
<sublink>plugin://plugin.video.SportsDevil/?mode=1&amp;item=catcher%3dstreams%26url=http://wizhdsports.fi/watch/Dallas_Mavericks_at_Atlanta_Hawks_live_NBA/nba5</sublink></link>
<referer></referer>
<thumbnail></thumbnail>
<fanart></fanart>
</plugin>
<item>
<title>[COLORred][B]00:30 - 03:30 [/COLOR][/B][COLORwhite][B]NBA Chicago Bulls at Boston Celtics [/COLOR][/B]</title>
<info>[COLORyellow][B]NBA[/COLOR][/B]</info>
<link>
<sublink>plugin://plugin.video.SportsDevil/?mode=1&amp;item=catcher%3dstreams%26url=http://wizhdsports.fi/watch/Chicago_Bulls_at_Boston_Celtics_live_NBA/nba6</sublink></link>
<referer></referer>
<thumbnail></thumbnail>
<fanart></fanart>
</plugin>
<item>
<title>[COLORred][B]01:00 - 04:00 [/COLOR][/B][COLORwhite][B]NBA New Orleans Pelicans at Miami Heat [/COLOR][/B]</title>
<info>[COLORyellow][B]NBA[/COLOR][/B]</info>
<link>
<sublink>plugin://plugin.video.SportsDevil/?mode=1&amp;item=catcher%3dstreams%26url=http://wizhdsports.fi/watch/New_Orleans_Pelicans_at_Miami_Heat_live_NBA/nba7</sublink></link>
<referer></referer>
<thumbnail></thumbnail>
<fanart></fanart>
</plugin>
<item>
<title>[COLORred][B]01:00 - 04:00 [/COLOR][/B][COLORwhite][B]NBA LA Clippers at Memphis Grizzlies [/COLOR][/B]</title>
<info>[COLORyellow][B]NBA[/COLOR][/B]</info>
<link>
<sublink>plugin://plugin.video.SportsDevil/?mode=1&amp;item=catcher%3dstreams%26url=http://wizhdsports.fi/watch/LA_Clippers_at_Memphis_Grizzlies_live_NBA/nba8</sublink></link>
<referer></referer>
<thumbnail></thumbnail>
<fanart></fanart>
</plugin>
<item>
<title>[COLORred][B]01:00 - 04:00 [/COLOR][/B][COLORwhite][B]NBA Oklahoma City Thunder at Utah Jazz [/COLOR][/B]</title>
<info>[COLORyellow][B]NBA[/COLOR][/B]</info>
<link>
<sublink>plugin://plugin.video.SportsDevil/?mode=1&amp;item=catcher%3dstreams%26url=http://wizhdsports.fi/watch/Oklahoma_City_Thunder_at_Utah_Jazz_live_NBA/nba9</sublink></link>
<referer></referer>
<thumbnail></thumbnail>
<fanart></fanart>
</plugin>
<item>
<title>[COLORred][B]01:00 - 04:00 [/COLOR][/B][COLORwhite][B]NHL Washington Capitals at Vegas Golden Knights [/COLOR][/B]</title>
<info>[COLORyellow][B]Hockey[/COLOR][/B]</info>
<link>
<sublink>plugin://plugin.video.SportsDevil/?mode=1&amp;item=catcher%3dstreams%26url=http://wizhdsports.fi/watch/Washington_Capitals_at_Vegas_Golden_Knights_live_Hockey/nhl11</sublink></link>
<referer></referer>
<thumbnail></thumbnail>
<fanart></fanart>
</plugin>
<item>
<title>[COLORred][B]01:00 - 04:00 [/COLOR][/B][COLORwhite][B]NHL Colorado Avalanche at Arizona Coyotes [/COLOR][/B]</title><info>[COLORyellow][B]Hockey[/COLOR][/B]</info>
<link>
<sublink>plugin://plugin.video.SportsDevil/?mode=1&amp;item=catcher%3dstreams%26url=http://wizhdsports.fi/watch/Colorado_Avalanche_at_Arizona_Coyotes_live_Hockey/nhl12</sublink></link>
<referer></referer>
<thumbnail></thumbnail>
<fanart></fanart>
</plugin>
<item>
<title>[COLORred][B]01:00 - 04:00 [/COLOR][/B][COLORwhite][B]NHL Nashville Predators at Dallas Stars [/COLOR][/B]</title>
<info>[COLORyellow][B]Hockey[/COLOR][/B]</info>
<link>
<sublink>plugin://plugin.video.SportsDevil/?mode=1&amp;item=catcher%3dstreams%26url=http://wizhdsports.fi/watch/Nashville_Predators_at_Dallas_Stars_live_Hockey/nfl4</sublink></link>
<referer></referer>
<thumbnail></thumbnail>
<fanart></fanart>
</plugin>
<item>
<title>[COLORred][B]01:30 - 04:30 [/COLOR][/B][COLORwhite][B]NBA Denver Nuggets at Golden State Warriors [/COLOR][/B]</title>
<info>[COLORyellow][B]NBA[/COLOR][/B]</info>
<link>
<sublink>plugin://plugin.video.SportsDevil/?mode=1&amp;item=catcher%3dstreams%26url=http://wizhdsports.fi/watch/Denver_Nuggets_at_Golden_State_Warriors_live_NBA/nba10</sublink></link>
<referer></referer>
<thumbnail></thumbnail>
<fanart></fanart>
</plugin>
<item>
<title>[COLORred][B]01:30 - 05:00 [/COLOR][/B][COLORwhite][B]NFL Minnesota Vikings at Green Bay Packers [/COLOR][/B]</title>
<info>[COLORyellow][B]NFL[/COLOR][/B]</info>
<link>
<sublink>plugin://plugin.video.SportsDevil/?mode=1&amp;item=catcher%3dstreams%26url=http://wizhdsports.fi/watch/Minnesota_Vikings_at_Green_Bay_Packers_live_NFL/skysportsmainevent</sublink></link>
<referer></referer>
<thumbnail></thumbnail>
<fanart></fanart>
</plugin>
<item>
<title>[COLORred][B]02:00 - 05:00 [/COLOR][/B][COLORwhite][B]NBA Minnesota Timberwolves at Phoenix Suns [/COLOR][/B]</title>
<info>[COLORyellow][B]NBA[/COLOR][/B]</info>
<link>
<sublink>plugin://plugin.video.SportsDevil/?mode=1&amp;item=catcher%3dstreams%26url=http://wizhdsports.fi/watch/Minnesota_Timberwolves_at_Phoenix_Suns_live_NBA/nfl3</sublink></link>
<referer></referer>
<thumbnail></thumbnail>
<fanart></fanart>
</plugin>
<item>
<title>[COLORred][B]02:30 - 05:30 [/COLOR][/B][COLORwhite][B]NBA Portland Trail Blazers at LA Lakers [/COLOR][/B]</title>
<info>[COLORyellow][B]NBA[/COLOR][/B]</info>
<link>
<sublink>plugin://plugin.video.SportsDevil/?mode=1&amp;item=catcher%3dstreams%26url=http://wizhdsports.fi/watch/Portland_Trail_Blazers_at_LA_Lakers_live_NBA/nba11</sublink></link>
<referer></referer>
<thumbnail></thumbnail>
<fanart></fanart>
</plugin>
<item>
<title>[COLORred][B]03:00 - 06:00 [/COLOR][/B][COLORwhite][B]NBA San Antonio Spurs at Sacramento Kings [/COLOR][/B]</title><info>[COLORyellow][B]NBA[/COLOR][/B]</info>
<link>
<sublink>plugin://plugin.video.SportsDevil/?mode=1&amp;item=catcher%3dstreams%26url=http://wizhdsports.fi/watch/San_Antonio_Spurs_at_Sacramento_Kings_live_NBA/nba12</sublink></link>
<referer></referer>
<thumbnail></thumbnail>
<fanart></fanart>
</plugin>
<item>
<title>[COLORred][B]03:00 - 06:00 [/COLOR][/B][COLORwhite][B]NHL St. Louis Blues at Vancouver Canucks [/COLOR][/B]</title>
<info>[COLORyellow][B]Hockey[/COLOR][/B]</info>
<link>
<sublink>plugin://plugin.video.SportsDevil/?mode=1&amp;item=catcher%3dstreams%26url=http://wizhdsports.fi/watch/St_Louis_Blues_at_Vancouver_Canucks_live_Hockey/nfl5</sublink></link>
<referer></referer>
<thumbnail></thumbnail>
<fanart></fanart>
</plugin>
<item>
<title>[COLORred][B]03:00 - 06:00 [/COLOR][/B][COLORwhite][B]NHL Los Angeles Kings at San Jose Sharks [/COLOR][/B]</title>
<info>[COLORyellow][B]Hockey[/COLOR][/B]</info>
<link>
<sublink>plugin://plugin.video.SportsDevil/?mode=1&amp;item=catcher%3dstreams%26url=http://wizhdsports.fi/watch/Los_Angeles_Kings_at_San_Jose_Sharks_live_Hockey/nfl6</sublink></link>
<referer></referer>
<thumbnail></thumbnail>
<fanart></fanart>
</plugin>
