<item>
<title>[COLORred][B]ALL DAY [/COLOR][/B][COLORwhite][B]Darts - Lakeside 2018 Darts Championship [/COLOR][/B]</title>
<info>[COLORyellow][B]Football[/COLOR][/B]</info>
<link>
<sublink>http://streams.yo.tv/srv3/ngrp:3.stream_all/chunklist_b1046000_DVR.m3u8</sublink>
<sublink>http://uk.stream.yo.tv/livehttporigin/Channel4_360p.stream/chunklist.m3u8</sublink></link>
<referer></referer>
<thumbnail></thumbnail>
<fanart></fanart>
</item>
<item>
<title>[COLORred][B]12:45 - 14:45 [/COLOR][/B][COLORwhite][B]England - FA Cup Fleetwood Town vs Leicester City [/COLOR][/B]</title>
<info>[COLORyellow][B]Football[/COLOR][/B]</info>
<link>
<sublink>http://a.files.bbci.co.uk/media/live/manifesto/audio_video/simulcast/hls/uk/abr_hdtv/ak/bbc_one_hd.m3u8</sublink>
<sublink>http://genti1.genti.stream/9ad8a768e95e09a43be43fccce63f893.m3u8</sublink>
<sublink>http://185.231.160.35/29/3/index.m3u8</sublink>
<sublink>https://ssh101.com/m3u8/dyn/united4all/index.m3u8</sublink>
<sublink>http://a.files.bbci.co.uk/media/live/manifesto/audio_video/simulcast/hls/uk/abr_hdtv/ak/bbc_one_scotland_hd.m3u8</sublink>
<sublink>http://a.files.bbci.co.uk/media/live/manifesto/audio_video/simulcast/hls/uk/abr_hdtv/ak/bbc_one_wales_hd.m3u8</sublink>
<sublink>http://a.files.bbci.co.uk/media/live/manifesto/audio_video/simulcast/hls/uk/abr_hdtv/ak/bbc_one_northern_ireland_hd.m3u8</sublink>
<sublink>plugin://plugin.video.SportsDevil/?mode=1&amp;item=catcher%3dstreams%26url=http://www.sdw-net.me/channels/Sportsnet-World.html</sublink>
<sublink>http://a.files.bbci.co.uk/media/live/manifesto/audio_video/simulcast/hls/uk/hls_tablet/ak/bbc_one_london.m3u8</sublink></link>
<sublink>plugin://plugin.video.SportsDevil/?mode=1&amp;item=catcher%3dstreams%26url=http://wizhdsports.fi/watch/Fleetwood_Town_vs_Leicester_City_live_Football/stream1</sublink></link>
<referer></referer>
<thumbnail></thumbnail>
<fanart></fanart>
</item>
<item>
<title>[COLORred][B]15:00 - 17:00 [/COLOR][/B][COLORwhite][B]England - FA Cup Exeter City vs West Bromwich Albion [/COLOR][/B]</title>
<info>[COLORyellow][B]Football[/COLOR][/B]</info>
<link>
<sublink>http://46.29.163.100/live7/tracks-v1a1/index.m3u8</sublink>
<sublink>plugin://plugin.video.SportsDevil/?mode=1&amp;item=catcher%3dstreams%26url=http://wizhdsports.fi/watch/Exeter_City_vs_West_Bromwich_Albion_live_Football/stream35</sublink></link>
<referer></referer>
<thumbnail></thumbnail>
<fanart></fanart>
</item>
<item>
<title>[COLORred][B]15:00 - 17:00 [/COLOR][/B][COLORwhite][B]England - FA Cup Fulham vs Southampton [/COLOR][/B]</title>
<info>[COLORyellow][B]Football[/COLOR][/B]</info>
<link>
<sublink>http://46.29.163.100/live1/tracks-v1a1/index.m3u8</sublink>
<sublink>plugin://plugin.video.SportsDevil/?mode=1&amp;item=catcher%3dstreams%26url=http://wizhdsports.fi/watch/Fulham_vs_Southampton_live_Football/stream2</sublink></link><referer></referer>
<thumbnail></thumbnail>
<fanart></fanart>
</item>
<item>
<title>[COLORred][B]15:00 - 17:00 [/COLOR][/B][COLORwhite][B]England - FA Cup Manchester City vs Burnley [/COLOR][/B]</title>
<info>[COLORyellow][B]Football[/COLOR][/B]</info>
<link>
<sublink>http://46.29.163.100/live2/tracks-v1a1/index.m3u8</sublink>
<sublink>http://185.231.160.35/29/3/index.m3u8</sublink>
<sublink>plugin://plugin.video.SportsDevil/?mode=1&amp;item=catcher%3dstreams%26url=http://wizhdsports.fi/watch/Manchester_City_vs_Burnley_live_Football/stream1</sublink></link>
<referer></referer>
<thumbnail></thumbnail>
<fanart></fanart>
</item>
<plugin>
<title>[COLORred][B]17:00 - 20:00 [/COLOR][/B][COLORwhite][B]Live CFB: FCS Championship [/COLOR][/B]</title>
<info>[COLORyellow][B]American Football[/COLOR][/B]</info>
<link>
<sublink>plugin://plugin.video.SportsDevil/?mode=1&amp;item=catcher%3dstreams%26url=http://www.sdw-net.me/channels/ESPN-US.html</sublink>
<sublink>plugin://plugin.video.SportsDevil/?mode=1&amp;item=catcher%3dstreams%26url=http://www.sdw-net.me/channels/BT-Sport-ESPN.html</sublink>
<sublink>plugin://plugin.video.SportsDevil/?mode=1&amp;item=catcher%3dstreams%26url=http://wizhdsports.fi/watch/Live_CFB_FCS_Championship_live_American_Football/stream37</sublink></link>
<referer></referer>
<thumbnail></thumbnail>
<fanart></fanart>
</plugin>
<plugin>
<title>[COLORred][B]17:30 - 19:30 [/COLOR][/B][COLORwhite][B]England - FA Cup Norwich City vs Chelsea [/COLOR][/B]</title>
<info>[COLORyellow][B]Football[/COLOR][/B]</info>
<link>
<sublink>plugin://plugin.video.SportsDevil/?mode=1&amp;item=catcher%3dstreams%26url=http://www.sdw-net.me/channels/Sportsnet-World.html</sublink>
<sublink>plugin://plugin.video.SportsDevil/?mode=1&amp;item=catcher%3dstreams%26url=http://www.sdw-net.me/channels/Bein-Sports-2.html</sublink>
<sublink>plugin://plugin.video.SportsDevil/?mode=1&amp;item=catcher%3dstreams%26url=http://www.sdw-net.me/channels/Bein-Sports-11.html</sublink>
<sublink>plugin://plugin.video.SportsDevil/?mode=1&amp;item=catcher%3dstreams%26url=http://www.sdw-net.me/channels/BT-Sport-2.html</sublink>
<sublink>plugin://plugin.video.SportsDevil/?mode=1&amp;item=catcher%3dstreams%26url=http://wizhdsports.fi/watch/Norwich_City_vs_Chelsea_live_Football/stream1</sublink></link>
<referer></referer>
<thumbnail></thumbnail>
<fanart></fanart>
</plugin>
<plugin>
<title>[COLORred][B]18:00 - 21:00 [/COLOR][/B][COLORwhite][B]NHL St. Louis Blues at Philadelphia Flyers [/COLOR][/B]</title>
<info>[COLORyellow][B]Hockey[/COLOR][/B]</info>
<link>
<sublink>plugin://plugin.video.SportsDevil/?mode=1&amp;item=catcher%3dstreams%26url=http://wizhdsports.fi/watch/St_Louis_Blues_at_Philadelphia_Flyers_live_Hockey/nhl1</sublink></link>
<referer></referer>
<thumbnail></thumbnail>
<fanart></fanart>
</plugin>
<plugin>
<title>[COLORred][B]20:00 - 23:00 [/COLOR][/B][COLORwhite][B]NHL Edmonton Oilers at Dallas Stars [/COLOR][/B]</title>
<info>[COLORyellow][B]Hockey[/COLOR][/B]</info>
<link>
<sublink>plugin://plugin.video.SportsDevil/?mode=1&amp;item=catcher%3dstreams%26url=http://wizhdsports.fi/watch/Edmonton_Oilers_at_Dallas_Stars_live_Hockey/nhl2</sublink></link>
<referer></referer>
<thumbnail></thumbnail>
<fanart></fanart>
</plugin>
<plugin>
<title>[COLORred][B]21:00 - 01:00 [/COLOR][/B][COLORwhite][B]NFL Tennessee Titans at Kansas City Chiefs [/COLOR][/B]</title>
<info>[COLORyellow][B]NFL[/COLOR][/B]</info>
<link>
<sublink>plugin://plugin.video.SportsDevil/?mode=1&amp;item=catcher%3dstreams%26url=http://wizhdsports.fi/watch/Tennessee_Titans_at_Kansas_City_Chiefs_live_NFL/nfl1</sublink></link>
<referer></referer>
<thumbnail></thumbnail>
<fanart></fanart>
</plugin>
<plugin>
<title>[COLORred][B]23:00 - 00:15 [/COLOR][/B][COLORwhite][B]Live College Basketball: Indiana - Minnesota [/COLOR][/B]</title>
<info>[COLORyellow][B]Basketball[/COLOR][/B]</info>
<link>
<sublink>plugin://plugin.video.SportsDevil/?mode=1&amp;item=catcher%3dstreams%26url=http://www.sdw-net.me/channels/ESPN-US.html</sublink>
<sublink>plugin://plugin.video.SportsDevil/?mode=1&amp;item=catcher%3dstreams%26url=http://www.sdw-net.me/channels/BT-Sport-ESPN.html</sublink>
<sublink>plugin://plugin.video.SportsDevil/?mode=1&amp;item=catcher%3dstreams%26url=http://wizhdsports.fi/watch/Live_CBB_Indiana_-_Minnesota_live_Basketball/stream37</sublink></link>
<referer></referer>
<thumbnail></thumbnail>
<fanart></fanart>
</plugin>
<plugin>
<title>[COLORred][B]00:00 - 03:00 [/COLOR][/B][COLORwhite][B]NHL Carolina Hurricanes at Boston Bruins [/COLOR][/B]</title>
<info>[COLORyellow][B]Hockey[/COLOR][/B]</info>
<link>
<sublink>plugin://plugin.video.SportsDevil/?mode=1&amp;item=catcher%3dstreams%26url=http://wizhdsports.fi/watch/Carolina_Hurricanes_at_Boston_Bruins_live_Hockey/nhl3</sublink></link>
<referer></referer>
<thumbnail></thumbnail>
<fanart></fanart>
</plugin>
<plugin>
<title>[COLORred][B]00:00 - 03:00 [/COLOR][/B][COLORwhite][B]NHL Vancouver Canucks at Toronto Maple Leafs [/COLOR][/B]</title>
<info>[COLORyellow][B]Hockey[/COLOR][/B]</info>
<link>
<sublink>plugin://plugin.video.SportsDevil/?mode=1&amp;item=catcher%3dstreams%26url=http://wizhdsports.fi/watch/Vancouver_Canucks_at_Toronto_Maple_Leafs_live_Hockey/nhl4</sublink></link>
<referer></referer>
<thumbnail></thumbnail>
<fanart></fanart>
</plugin>
<plugin>
<title>[COLORred][B]00:00 - 03:00 [/COLOR][/B][COLORwhite][B]NHL Tampa Bay Lightning at Ottawa Senators [/COLOR][/B]</title>
<info>[COLORyellow][B]Hockey[/COLOR][/B]</info>
<link>
<sublink>plugin://plugin.video.SportsDevil/?mode=1&amp;item=catcher%3dstreams%26url=http://wizhdsports.fi/watch/Tampa_Bay_Lightning_at_Ottawa_Senators_live_Hockey/nhl5</sublink></link>
<referer></referer>
<thumbnail></thumbnail>
<fanart></fanart>
</plugin>
<plugin>
<title>[COLORred][B]01:00 - 04:00 [/COLOR][/B][COLORwhite][B]NHL New York Rangers at Arizona Coyotes [/COLOR][/B]</title>
<info>[COLORyellow][B]Hockey[/COLOR][/B]</info>
<link>
<sublink>plugin://plugin.video.SportsDevil/?mode=1&amp;item=catcher%3dstreams%26url=http://wizhdsports.fi/watch/New_York_Rangers_at_Arizona_Coyotes_live_Hockey/nhl6</sublink></link>
<referer></referer>
<thumbnail></thumbnail>
<fanart></fanart>
</plugin>
<plugin>
<title>[COLORred][B]01:00 - 05:00 [/COLOR][/B][COLORwhite][B]NFL Atlanta Falcons at Los Angeles Rams [/COLOR][/B]</title>
<info>[COLORyellow][B]NFL[/COLOR][/B]</info>
<link>
<sublink>plugin://plugin.video.SportsDevil/?mode=1&amp;item=catcher%3dstreams%26url=http://wizhdsports.fi/watch/Atlanta_Falcons_at_Los_Angeles_Rams_live_NFL/nfl2</sublink></link>
<referer></referer>
<thumbnail></thumbnail>
<fanart></fanart>
</plugin>
<plugin>
<title>[COLORred][B]02:00 - 05:00 [/COLOR][/B][COLORwhite][B]NHL Minnesota Wild at Colorado Avalanche [/COLOR][/B]</title>
<info>[COLORyellow][B]Hockey[/COLOR][/B]</info>
<link>
<sublink>plugin://plugin.video.SportsDevil/?mode=1&amp;item=catcher%3dstreams%26url=http://wizhdsports.fi/watch/Minnesota_Wild_at_Colorado_Avalanche_live_Hockey/nhl7</sublink></link>
<referer></referer>
<thumbnail></thumbnail>
<fanart></fanart>
</plugin>
<plugin>
<title>[COLORred][B]03:00 - 06:00 [/COLOR][/B][COLORwhite][B]NBA Denver Nuggets at Sacramento Kings [/COLOR][/B]</title>
<info>[COLORyellow][B]NBA[/COLOR][/B]</info>
<link>
<sublink>plugin://plugin.video.SportsDevil/?mode=1&amp;item=catcher%3dstreams%26url=http://wizhdsports.fi/watch/Denver_Nuggets_at_Sacramento_Kings_live_NBA/nba8</sublink></link>
<referer></referer>
<thumbnail></thumbnail>
<fanart></fanart>
</plugin>
<plugin>
<title>[COLORred][B]03:00 - 06:00 [/COLOR][/B][COLORwhite][B]NHL Anaheim Ducks at Calgary Flames [/COLOR][/B]</title>
<info>[COLORyellow][B]Hockey[/COLOR][/B]</info>
<link>
<sublink>plugin://plugin.video.SportsDevil/?mode=1&amp;item=catcher%3dstreams%26url=http://wizhdsports.fi/watch/Anaheim_Ducks_at_Calgary_Flames_live_Hockey/nhl8</sublink></link>
<referer></referer>
<thumbnail></thumbnail>
<fanart></fanart>
</plugin>
<plugin>
<title>[COLORred][B]03:30 - 06:30 [/COLOR][/B][COLORwhite][B]NHL Nashville Predators at Los Angeles Kings [/COLOR][/B]</title>
<info>[COLORyellow][B]Hockey[/COLOR][/B]</info>
<link>
<sublink>plugin://plugin.video.SportsDevil/?mode=1&amp;item=catcher%3dstreams%26url=http://wizhdsports.fi/watch/Nashville_Predators_at_Los_Angeles_Kings_live_Hockey/nhl9</sublink></link>
<referer></referer>
<thumbnail></thumbnail>
<fanart></fanart>
</plugin>
