<plugin>
<title>[COLORred][B]19:45 - 21:45 [/COLOR][/B][COLORwhite][B]Scotland - Scottish Premiership Celtic vs Dundee [/COLOR][/B]</title>
<info>[COLORyellow][B]Football[/COLOR][/B]</info>
<link>
<sublink>plugin://plugin.video.SportsDevil/?mode=1&amp;item=catcher%3dstreams%26url=http://wizhdsports.fi/watch/Celtic_vs_Dundee_live_Football/stream6</sublink></link>
<referer></referer>
<thumbnail></thumbnail>
<fanart></fanart>
</plugin>
<plugin>
<title>[COLORred][B]19:45 - 21:45 [/COLOR][/B][COLORwhite][B]Scotland - Scottish Premiership Motherwell vs Aberdeen [/COLOR][/B]</title>
<info>[COLORyellow][B]Football[/COLOR][/B]</info>
<link>
<sublink>plugin://plugin.video.SportsDevil/?mode=1&amp;item=catcher%3dstreams%26url=http://wizhdsports.fi/watch/Motherwell_vs_Aberdeen_live_Football/skysportsmainevent</sublink></link>
<referer></referer>
<thumbnail></thumbnail>
<fanart></fanart>
</plugin>
<plugin>
<title>[COLORred][B]19:45 - 21:45 [/COLOR][/B][COLORwhite][B]Italy - Coppa Italia Lazio vs Milan [/COLOR][/B]</title>
<info>[COLORyellow][B]Football[/COLOR][/B]</info>
<link>
<sublink>plugin://plugin.video.SportsDevil/?mode=1&amp;item=catcher%3dstreams%26url=http://wizhdsports.fi/watch/Lazio_vs_Milan_live_Football/stream11</sublink></link>
<referer></referer>
<thumbnail></thumbnail>
<fanart></fanart>
</plugin>
<plugin>
<title>[COLORred][B]20:05 - 22:05 [/COLOR][/B][COLORwhite][B]England - FA Cup Tottenham Hotspur vs Rochdale [/COLOR][/B]</title>
<info>[COLORyellow][B]Football[/COLOR][/B]</info>
<link>
<sublink>plugin://plugin.video.SportsDevil/?mode=1&amp;item=catcher%3dstreams%26url=http://wizhdsports.fi/watch/Tottenham_Hotspur_vs_Rochdale_live_Football/stream1</sublink></link>
<referer></referer>
<thumbnail></thumbnail>
<fanart></fanart>
</plugin>